exp/__init__.py
exp/__version__.py
exp/args.py
exp/gopt.py
exp/params.py
exp/run.py
test/__init__.py
test/test_params.py
test/assets/__init__.py
test/assets/dummy_runnable.py
test/assets/runnable_tensorflow.py
exp-0.5.1.dist-info/LICENSE
exp-0.5.1.dist-info/METADATA
exp-0.5.1.dist-info/WHEEL
exp-0.5.1.dist-info/top_level.txt
exp-0.5.1.dist-info/RECORD
