Metadata-Version: 2.1
Name: exp
Version: 0.5.1
Summary: Python tool do design and run experiments with global optimisation and grid search
Home-page: https://github.com/davidenunes/exp
Author: Davide Nunes
Author-email: mail@davidenunes.com
License: Apache 2.0
Platform: UNKNOWN
Classifier: Programming Language :: Python
Classifier: Programming Language :: Python :: 3.6
Classifier: Programming Language :: Python :: 3.7
Requires-Python: >=3.6
Requires-Dist: toml
Requires-Dist: click
Requires-Dist: numpy
Requires-Dist: matplotlib
Requires-Dist: GPUtil
Requires-Dist: scikit-optimize
